{
    "response": [
        {
            "maintainer": "Bava7325",
            "oem": "realme",
            "device": "realme 5 Pro",
            "version": "7.0",
            "codename": "Patience",
            "filename": "AfterLife-V7.0-Patience-OFFICIAL-RMX1971-20240812-Vanilla.zip",
            "download": "https://sourceforge.net/projects/afterlife-projects/files/release/RMX1971/AfterLife-V7.0-Patience-OFFICIAL-RMX1971-20240812-Vanilla.zip/download",
            "timestamp": 1723454360,
            "md5": "29a2a38b07f35f3615d3123eb7f5334e",
            "sha256": "7c078f381aa902b43cb9857f9e1a755eb20380aece65566f287ce11f53b705ad",
            "size": 1433785586,
            "buildtype": "OFFICIAL",
            "forum": "https://t.me/Realme5Pro_Global",
            "telegram": "https://t.me/Bava7325"
        }
    ]
}
